{
    "forge_marker": 1,
    "defaults": {
        "model": "sgcraft:zpm_interface_cart",
        "transform": "forge:default-block"
    },
    "variants": {
        "inventory": [
            {
                "model": "sgcraft:zpm_interface_cart"
            }
        ],
        "facing": {
            "south": {
                "y": 180.0
            },
            "west": {
                "y": 270.0
            },
            "north": {},
            "east": {
                "y": 90.0
            }
        },
        "zpm": {
            "true": {
                "model": "sgcraft:zpm_interface_cart_active"
            },
            "false": {
                "model": "sgcraft:zpm_interface_cart"
            }
        }
    }
}